[
    {
        "data": "חיפה - קריית חיים ושמואל",
        "date": "24.11.2024",
        "time": "18:12:22",
        "alertDate": "2024-11-24T18:12:00",
        "category": 1,
        "category_desc": "ירי רקטות וטילים",
        "matrix_id": 1,
        "rid": 52376,
        "NAME_HE": "חיפה - קריית חיים ושמואל",
        "NAME_EN": "Haifa - Kiryat Haim and Shmuel ",
        "NAME_AR": "حيفا - كريات حاييم وشموئيل",
        "NAME_RU": "Хайфа - Кирьят Хаим и Шмуэль"
    },
    {
        "data": "חיפה - קריית חיים ושמואל",
        "date": "24.11.2024",
        "time": "13:04:31",
        "alertDate": "2024-11-24T13:05:00",
        "category": 1,
        "category_desc": "ירי רקטות וטילים",
        "matrix_id": 1,
        "rid": 52214,
        "NAME_HE": "חיפה - קריית חיים ושמואל",
        "NAME_EN": "Haifa - Kiryat Haim and Shmuel ",
        "NAME_AR": "حيفا - كريات حاييم وشموئيل",
        "NAME_RU": "Хайфа - Кирьят Хаим и Шмуэль"
    },
    {
        "data": "חיפה - קריית חיים ושמואל",
        "date": "23.11.2024",
        "time": "04:18:55",
        "alertDate": "2024-11-23T04:19:00",
        "category": 1,
        "category_desc": "ירי רקטות וטילים",
        "matrix_id": 1,
        "rid": 51867,
        "NAME_HE": "חיפה - קריית חיים ושמואל",
        "NAME_EN": "Haifa - Kiryat Haim and Shmuel ",
        "NAME_AR": "حيفا - كريات حاييم وشموئيل",
        "NAME_RU": "Хайфа - Кирьят Хаим и Шмуэль"
    },
    {
        "data": "חיפה - קריית חיים ושמואל",
        "date": "22.11.2024",
        "time": "02:09:03",
        "alertDate": "2024-11-22T02:09:00",
        "category": 1,
        "category_desc": "ירי רקטות וטילים",
        "matrix_id": 1,
        "rid": 51705,
        "NAME_HE": "חיפה - קריית חיים ושמואל",
        "NAME_EN": "Haifa - Kiryat Haim and Shmuel ",
        "NAME_AR": "حيفا - كريات حاييم وشموئيل",
        "NAME_RU": "Хайфа - Кирьят Хаим и Шмуэль"
    },
    {
        "data": "חיפה - קריית חיים ושמואל",
        "date": "16.11.2024",
        "time": "19:45:15",
        "alertDate": "2024-11-16T19:45:00",
        "category": 1,
        "category_desc": "ירי רקטות וטילים",
        "matrix_id": 1,
        "rid": 51048,
        "NAME_HE": "חיפה - קריית חיים ושמואל",
        "NAME_EN": "Haifa - Kiryat Haim and Shmuel ",
        "NAME_AR": "حيفا - كريات حاييم وشموئيل",
        "NAME_RU": "Хайфа - Кирьят Хаим и Шмуэль"
    },
    {
        "data": "חיפה - קריית חיים ושמואל",
        "date": "16.11.2024",
        "time": "14:44:46",
        "alertDate": "2024-11-16T14:45:00",
        "category": 1,
        "category_desc": "ירי רקטות וטילים",
        "matrix_id": 1,
        "rid": 51015,
        "NAME_HE": "חיפה - קריית חיים ושמואל",
        "NAME_EN": "Haifa - Kiryat Haim and Shmuel ",
        "NAME_AR": "حيفا - كريات حاييم وشموئيل",
        "NAME_RU": "Хайфа - Кирьят Хаим и Шмуэль"
    },
    {
        "data": "חיפה - קריית חיים ושמואל",
        "date": "15.11.2024",
        "time": "09:01:24",
        "alertDate": "2024-11-15T09:01:00",
        "category": 1,
        "category_desc": "ירי רקטות וטילים",
        "matrix_id": 1,
        "rid": 50899,
        "NAME_HE": "חיפה - קריית חיים ושמואל",
        "NAME_EN": "Haifa - Kiryat Haim and Shmuel ",
        "NAME_AR": "حيفا - كريات حاييم وشموئيل",
        "NAME_RU": "Хайфа - Кирьят Хаим и Шмуэль"
    },
    {
        "data": "חיפה - קריית חיים ושמואל",
        "date": "15.11.2024",
        "time": "06:53:27",
        "alertDate": "2024-11-15T06:53:00",
        "category": 1,
        "category_desc": "ירי רקטות וטילים",
        "matrix_id": 1,
        "rid": 50868,
        "NAME_HE": "חיפה - קריית חיים ושמואל",
        "NAME_EN": "Haifa - Kiryat Haim and Shmuel ",
        "NAME_AR": "حيفا - كريات حاييم وشموئيل",
        "NAME_RU": "Хайфа - Кирьят Хаим и Шмуэль"
    },
    {
        "data": "חיפה - קריית חיים ושמואל",
        "date": "14.11.2024",
        "time": "15:53:58",
        "alertDate": "2024-11-14T15:54:00",
        "category": 1,
        "category_desc": "ירי רקטות וטילים",
        "matrix_id": 1,
        "rid": 50755,
        "NAME_HE": "חיפה - קריית חיים ושמואל",
        "NAME_EN": "Haifa - Kiryat Haim and Shmuel ",
        "NAME_AR": "حيفا - كريات حاييم وشموئيل",
        "NAME_RU": "Хайфа - Кирьят Хаим и Шмуэль"
    },
    {
        "data": "חיפה - קריית חיים ושמואל",
        "date": "12.11.2024",
        "time": "09:34:06",
        "alertDate": "2024-11-12T09:34:00",
        "category": 2,
        "category_desc": "חדירת כלי טיס עוין",
        "matrix_id": 6,
        "rid": 50282,
        "NAME_HE": "חיפה - קריית חיים ושמואל",
        "NAME_EN": "Haifa - Kiryat Haim and Shmuel ",
        "NAME_AR": "حيفا - كريات حاييم وشموئيل",
        "NAME_RU": "Хайфа - Кирьят Хаим и Шмуэль"
    },
    {
        "data": "חיפה - קריית חיים ושמואל",
        "date": "11.11.2024",
        "time": "15:42:21",
        "alertDate": "2024-11-11T15:42:00",
        "category": 1,
        "category_desc": "ירי רקטות וטילים",
        "matrix_id": 1,
        "rid": 50132,
        "NAME_HE": "חיפה - קריית חיים ושמואל",
        "NAME_EN": "Haifa - Kiryat Haim and Shmuel ",
        "NAME_AR": "حيفا - كريات حاييم وشموئيل",
        "NAME_RU": "Хайфа - Кирьят Хаим и Шмуэль"
    },
    {
        "data": "חיפה - קריית חיים ושמואל",
        "date": "08.11.2024",
        "time": "07:44:33",
        "alertDate": "2024-11-08T07:45:00",
        "category": 1,
        "category_desc": "ירי רקטות וטילים",
        "matrix_id": 1,
        "rid": 49628,
        "NAME_HE": "חיפה - קריית חיים ושמואל",
        "NAME_EN": "Haifa - Kiryat Haim and Shmuel ",
        "NAME_AR": "حيفا - كريات حاييم وشموئيل",
        "NAME_RU": "Хайфа - Кирьят Хаим и Шмуэль"
    },
    {
        "data": "חיפה - קריית חיים ושמואל",
        "date": "07.11.2024",
        "time": "16:16:47",
        "alertDate": "2024-11-07T16:17:00",
        "category": 1,
        "category_desc": "ירי רקטות וטילים",
        "matrix_id": 1,
        "rid": 49557,
        "NAME_HE": "חיפה - קריית חיים ושמואל",
        "NAME_EN": "Haifa - Kiryat Haim and Shmuel ",
        "NAME_AR": "حيفا - كريات حاييم وشموئيل",
        "NAME_RU": "Хайфа - Кирьят Хаим и Шмуэль"
    },
    {
        "data": "חיפה - קריית חיים ושמואל",
        "date": "07.11.2024",
        "time": "16:14:42",
        "alertDate": "2024-11-07T16:15:00",
        "category": 1,
        "category_desc": "ירי רקטות וטילים",
        "matrix_id": 1,
        "rid": 49529,
        "NAME_HE": "חיפה - קריית חיים ושמואל",
        "NAME_EN": "Haifa - Kiryat Haim and Shmuel ",
        "NAME_AR": "حيفا - كريات حاييم وشموئيل",
        "NAME_RU": "Хайфа - Кирьят Хаим и Шмуэль"
    },
    {
        "data": "חיפה - קריית חיים ושמואל",
        "date": "07.11.2024",
        "time": "13:47:07",
        "alertDate": "2024-11-07T13:47:00",
        "category": 1,
        "category_desc": "ירי רקטות וטילים",
        "matrix_id": 1,
        "rid": 49472,
        "NAME_HE": "חיפה - קריית חיים ושמואל",
        "NAME_EN": "Haifa - Kiryat Haim and Shmuel ",
        "NAME_AR": "حيفا - كريات حاييم وشموئيل",
        "NAME_RU": "Хайфа - Кирьят Хаим и Шмуэль"
    },
    {
        "data": "חיפה - קריית חיים ושמואל",
        "date": "05.11.2024",
        "time": "06:38:26",
        "alertDate": "2024-11-05T06:38:00",
        "category": 1,
        "category_desc": "ירי רקטות וטילים",
        "matrix_id": 1,
        "rid": 49025,
        "NAME_HE": "חיפה - קריית חיים ושמואל",
        "NAME_EN": "Haifa - Kiryat Haim and Shmuel ",
        "NAME_AR": "حيفا - كريات حاييم وشموئيل",
        "NAME_RU": "Хайфа - Кирьят Хаим и Шмуэль"
    },
    {
        "data": "חיפה - קריית חיים ושמואל",
        "date": "03.11.2024",
        "time": "17:33:40",
        "alertDate": "2024-11-03T17:34:00",
        "category": 2,
        "category_desc": "חדירת כלי טיס עוין",
        "matrix_id": 6,
        "rid": 48914,
        "NAME_HE": "חיפה - קריית חיים ושמואל",
        "NAME_EN": "Haifa - Kiryat Haim and Shmuel ",
        "NAME_AR": "حيفا - كريات حاييم وشموئيل",
        "NAME_RU": "Хайфа - Кирьят Хаим и Шмуэль"
    },
    {
        "data": "חיפה - קריית חיים ושמואל",
        "date": "02.11.2024",
        "time": "16:27:36",
        "alertDate": "2024-11-02T16:28:00",
        "category": 2,
        "category_desc": "חדירת כלי טיס עוין",
        "matrix_id": 6,
        "rid": 48774,
        "NAME_HE": "חיפה - קריית חיים ושמואל",
        "NAME_EN": "Haifa - Kiryat Haim and Shmuel ",
        "NAME_AR": "حيفا - كريات حاييم وشموئيل",
        "NAME_RU": "Хайфа - Кирьят Хаим и Шмуэль"
    },
    {
        "data": "חיפה - קריית חיים ושמואל",
        "date": "02.11.2024",
        "time": "08:22:05",
        "alertDate": "2024-11-02T08:22:00",
        "category": 2,
        "category_desc": "חדירת כלי טיס עוין",
        "matrix_id": 6,
        "rid": 48566,
        "NAME_HE": "חיפה - קריית חיים ושמואל",
        "NAME_EN": "Haifa - Kiryat Haim and Shmuel ",
        "NAME_AR": "حيفا - كريات حاييم وشموئيل",
        "NAME_RU": "Хайфа - Кирьят Хаим и Шмуэль"
    },
    {
        "data": "חיפה - קריית חיים ושמואל",
        "date": "02.11.2024",
        "time": "08:20:03",
        "alertDate": "2024-11-02T08:20:00",
        "category": 2,
        "category_desc": "חדירת כלי טיס עוין",
        "matrix_id": 6,
        "rid": 48556,
        "NAME_HE": "חיפה - קריית חיים ושמואל",
        "NAME_EN": "Haifa - Kiryat Haim and Shmuel ",
        "NAME_AR": "حيفا - كريات حاييم وشموئيل",
        "NAME_RU": "Хайфа - Кирьят Хаим и Шмуэль"
    },
    {
        "data": "חיפה - קריית חיים ושמואל",
        "date": "31.10.2024",
        "time": "15:12:50",
        "alertDate": "2024-10-31T15:13:00",
        "category": 1,
        "category_desc": "ירי רקטות וטילים",
        "matrix_id": 1,
        "rid": 48319,
        "NAME_HE": "חיפה - קריית חיים ושמואל",
        "NAME_EN": "Haifa - Kiryat Haim and Shmuel ",
        "NAME_AR": "حيفا - كريات حاييم وشموئيل",
        "NAME_RU": "Хайфа - Кирьят Хаим и Шмуэль"
    },
    {
        "data": "חיפה - קריית חיים ושמואל",
        "date": "30.10.2024",
        "time": "17:33:59",
        "alertDate": "2024-10-30T17:34:00",
        "category": 2,
        "category_desc": "חדירת כלי טיס עוין",
        "matrix_id": 6,
        "rid": 48191,
        "NAME_HE": "חיפה - קריית חיים ושמואל",
        "NAME_EN": "Haifa - Kiryat Haim and Shmuel ",
        "NAME_AR": "حيفا - كريات حاييم وشموئيل",
        "NAME_RU": "Хайфа - Кирьят Хаим и Шмуэль"
    },
    {
        "data": "חיפה - קריית חיים ושמואל",
        "date": "28.10.2024",
        "time": "15:13:55",
        "alertDate": "2024-10-28T15:14:00",
        "category": 1,
        "category_desc": "ירי רקטות וטילים",
        "matrix_id": 1,
        "rid": 47520,
        "NAME_HE": "חיפה - קריית חיים ושמואל",
        "NAME_EN": "Haifa - Kiryat Haim and Shmuel ",
        "NAME_AR": "حيفا - كريات حاييم وشموئيل",
        "NAME_RU": "Хайфа - Кирьят Хаим и Шмуэль"
    },
    {
        "data": "חיפה - קריית חיים ושמואל",
        "date": "25.10.2024",
        "time": "09:02:06",
        "alertDate": "2024-10-25T09:02:00",
        "category": 1,
        "category_desc": "ירי רקטות וטילים",
        "matrix_id": 1,
        "rid": 47094,
        "NAME_HE": "חיפה - קריית חיים ושמואל",
        "NAME_EN": "Haifa - Kiryat Haim and Shmuel ",
        "NAME_AR": "حيفا - كريات حاييم وشموئيل",
        "NAME_RU": "Хайфа - Кирьят Хаим и Шмуэль"
    },
    {
        "data": "חיפה - קריית חיים ושמואל",
        "date": "22.10.2024",
        "time": "18:27:57",
        "alertDate": "2024-10-22T18:28:00",
        "category": 2,
        "category_desc": "חדירת כלי טיס עוין",
        "matrix_id": 6,
        "rid": 46442,
        "NAME_HE": "חיפה - קריית חיים ושמואל",
        "NAME_EN": "Haifa - Kiryat Haim and Shmuel ",
        "NAME_AR": "حيفا - كريات حاييم وشموئيل",
        "NAME_RU": "Хайфа - Кирьят Хаим и Шмуэль"
    },
    {
        "data": "חיפה - קריית חיים ושמואל",
        "date": "22.10.2024",
        "time": "18:25:39",
        "alertDate": "2024-10-22T18:26:00",
        "category": 2,
        "category_desc": "חדירת כלי טיס עוין",
        "matrix_id": 6,
        "rid": 46436,
        "NAME_HE": "חיפה - קריית חיים ושמואל",
        "NAME_EN": "Haifa - Kiryat Haim and Shmuel ",
        "NAME_AR": "حيفا - كريات حاييم وشموئيل",
        "NAME_RU": "Хайфа - Кирьят Хаим и Шмуэль"
    },
    {
        "data": "חיפה - קריית חיים ושמואל",
        "date": "22.10.2024",
        "time": "04:52:07",
        "alertDate": "2024-10-22T04:52:00",
        "category": 1,
        "category_desc": "ירי רקטות וטילים",
        "matrix_id": 1,
        "rid": 46234,
        "NAME_HE": "חיפה - קריית חיים ושמואל",
        "NAME_EN": "Haifa - Kiryat Haim and Shmuel ",
        "NAME_AR": "حيفا - كريات حاييم وشموئيل",
        "NAME_RU": "Хайфа - Кирьят Хаим и Шмуэль"
    },
    {
        "data": "חיפה - קריית חיים ושמואל",
        "date": "21.10.2024",
        "time": "12:28:43",
        "alertDate": "2024-10-21T12:29:00",
        "category": 1,
        "category_desc": "ירי רקטות וטילים",
        "matrix_id": 1,
        "rid": 45972,
        "NAME_HE": "חיפה - קריית חיים ושמואל",
        "NAME_EN": "Haifa - Kiryat Haim and Shmuel ",
        "NAME_AR": "حيفا - كريات حاييم وشموئيل",
        "NAME_RU": "Хайфа - Кирьят Хаим и Шмуэль"
    },
    {
        "data": "חיפה - קריית חיים ושמואל",
        "date": "20.10.2024",
        "time": "16:02:39",
        "alertDate": "2024-10-20T16:03:00",
        "category": 2,
        "category_desc": "חדירת כלי טיס עוין",
        "matrix_id": 6,
        "rid": 45772,
        "NAME_HE": "חיפה - קריית חיים ושמואל",
        "NAME_EN": "Haifa - Kiryat Haim and Shmuel ",
        "NAME_AR": "حيفا - كريات حاييم وشموئيل",
        "NAME_RU": "Хайфа - Кирьят Хаим и Шмуэль"
    },
    {
        "data": "חיפה - קריית חיים ושמואל",
        "date": "20.10.2024",
        "time": "15:41:18",
        "alertDate": "2024-10-20T15:41:00",
        "category": 1,
        "category_desc": "ירי רקטות וטילים",
        "matrix_id": 1,
        "rid": 45715,
        "NAME_HE": "חיפה - קריית חיים ושמואל",
        "NAME_EN": "Haifa - Kiryat Haim and Shmuel ",
        "NAME_AR": "حيفا - كريات حاييم وشموئيل",
        "NAME_RU": "Хайфа - Кирьят Хаим и Шмуэль"
    },
    {
        "data": "חיפה - קריית חיים ושמואל",
        "date": "20.10.2024",
        "time": "09:38:40",
        "alertDate": "2024-10-20T09:39:00",
        "category": 1,
        "category_desc": "ירי רקטות וטילים",
        "matrix_id": 1,
        "rid": 45576,
        "NAME_HE": "חיפה - קריית חיים ושמואל",
        "NAME_EN": "Haifa - Kiryat Haim and Shmuel ",
        "NAME_AR": "حيفا - كريات حاييم وشموئيل",
        "NAME_RU": "Хайфа - Кирьят Хаим и Шмуэль"
    },
    {
        "data": "חיפה - קריית חיים ושמואל",
        "date": "19.10.2024",
        "time": "10:23:02",
        "alertDate": "2024-10-19T10:23:00",
        "category": 1,
        "category_desc": "ירי רקטות וטילים",
        "matrix_id": 1,
        "rid": 45395,
        "NAME_HE": "חיפה - קריית חיים ושמואל",
        "NAME_EN": "Haifa - Kiryat Haim and Shmuel ",
        "NAME_AR": "حيفا - كريات حاييم وشموئيل",
        "NAME_RU": "Хайфа - Кирьят Хаим и Шмуэль"
    },
    {
        "data": "חיפה - קריית חיים ושמואל",
        "date": "17.10.2024",
        "time": "07:28:17",
        "alertDate": "2024-10-17T07:28:00",
        "category": 1,
        "category_desc": "ירי רקטות וטילים",
        "matrix_id": 1,
        "rid": 45080,
        "NAME_HE": "חיפה - קריית חיים ושמואל",
        "NAME_EN": "Haifa - Kiryat Haim and Shmuel ",
        "NAME_AR": "حيفا - كريات حاييم وشموئيل",
        "NAME_RU": "Хайфа - Кирьят Хаим и Шмуэль"
    },
    {
        "data": "חיפה - קריית חיים ושמואל",
        "date": "15.10.2024",
        "time": "14:20:17",
        "alertDate": "2024-10-15T14:20:00",
        "category": 1,
        "category_desc": "ירי רקטות וטילים",
        "matrix_id": 1,
        "rid": 44739,
        "NAME_HE": "חיפה - קריית חיים ושמואל",
        "NAME_EN": "Haifa - Kiryat Haim and Shmuel ",
        "NAME_AR": "حيفا - كريات حاييم وشموئيل",
        "NAME_RU": "Хайфа - Кирьят Хаим и Шмуэль"
    },
    {
        "data": "חיפה - קריית חיים ושמואל",
        "date": "15.10.2024",
        "time": "07:27:51",
        "alertDate": "2024-10-15T07:28:00",
        "category": 1,
        "category_desc": "ירי רקטות וטילים",
        "matrix_id": 1,
        "rid": 44691,
        "NAME_HE": "חיפה - קריית חיים ושמואל",
        "NAME_EN": "Haifa - Kiryat Haim and Shmuel ",
        "NAME_AR": "حيفا - كريات حاييم وشموئيل",
        "NAME_RU": "Хайфа - Кирьят Хаим и Шмуэль"
    },
    {
        "data": "חיפה - קריית חיים ושמואל",
        "date": "14.10.2024",
        "time": "09:32:45",
        "alertDate": "2024-10-14T09:33:00",
        "category": 1,
        "category_desc": "ירי רקטות וטילים",
        "matrix_id": 1,
        "rid": 44185,
        "NAME_HE": "חיפה - קריית חיים ושמואל",
        "NAME_EN": "Haifa - Kiryat Haim and Shmuel ",
        "NAME_AR": "حيفا - كريات حاييم وشموئيل",
        "NAME_RU": "Хайфа - Кирьят Хаим и Шмуэль"
    },
    {
        "data": "חיפה - קריית חיים ושמואל",
        "date": "13.10.2024",
        "time": "08:59:58",
        "alertDate": "2024-10-13T09:00:00",
        "category": 1,
        "category_desc": "ירי רקטות וטילים",
        "matrix_id": 1,
        "rid": 43925,
        "NAME_HE": "חיפה - קריית חיים ושמואל",
        "NAME_EN": "Haifa - Kiryat Haim and Shmuel ",
        "NAME_AR": "حيفا - كريات حاييم وشموئيل",
        "NAME_RU": "Хайфа - Кирьят Хаим и Шмуэль"
    },
    {
        "data": "חיפה - קריית חיים ושמואל",
        "date": "12.10.2024",
        "time": "13:07:41",
        "alertDate": "2024-10-12T13:08:00",
        "category": 1,
        "category_desc": "ירי רקטות וטילים",
        "matrix_id": 1,
        "rid": 43774,
        "NAME_HE": "חיפה - קריית חיים ושמואל",
        "NAME_EN": "Haifa - Kiryat Haim and Shmuel ",
        "NAME_AR": "حيفا - كريات حاييم وشموئيل",
        "NAME_RU": "Хайфа - Кирьят Хаим и Шмуэль"
    },
    {
        "data": "חיפה - קריית חיים ושמואל",
        "date": "09.10.2024",
        "time": "13:11:06",
        "alertDate": "2024-10-09T13:11:00",
        "category": 1,
        "category_desc": "ירי רקטות וטילים",
        "matrix_id": 1,
        "rid": 43199,
        "NAME_HE": "חיפה - קריית חיים ושמואל",
        "NAME_EN": "Haifa - Kiryat Haim and Shmuel ",
        "NAME_AR": "حيفا - كريات حاييم وشموئيل",
        "NAME_RU": "Хайфа - Кирьят Хаим и Шмуэль"
    },
    {
        "data": "חיפה - קריית חיים ושמואל",
        "date": "08.10.2024",
        "time": "12:44:34",
        "alertDate": "2024-10-08T12:45:00",
        "category": 1,
        "category_desc": "ירי רקטות וטילים",
        "matrix_id": 1,
        "rid": 43069,
        "NAME_HE": "חיפה - קריית חיים ושמואל",
        "NAME_EN": "Haifa - Kiryat Haim and Shmuel ",
        "NAME_AR": "حيفا - كريات حاييم وشموئيل",
        "NAME_RU": "Хайфа - Кирьят Хаим и Шмуэль"
    },
    {
        "data": "חיפה - קריית חיים ושמואל",
        "date": "08.10.2024",
        "time": "12:14:17",
        "alertDate": "2024-10-08T12:14:00",
        "category": 1,
        "category_desc": "ירי רקטות וטילים",
        "matrix_id": 1,
        "rid": 43050,
        "NAME_HE": "חיפה - קריית חיים ושמואל",
        "NAME_EN": "Haifa - Kiryat Haim and Shmuel ",
        "NAME_AR": "حيفا - كريات حاييم وشموئيل",
        "NAME_RU": "Хайфа - Кирьят Хаим и Шмуэль"
    },
    {
        "data": "חיפה - קריית חיים ושמואל",
        "date": "08.10.2024",
        "time": "12:11:15",
        "alertDate": "2024-10-08T12:11:00",
        "category": 1,
        "category_desc": "ירי רקטות וטילים",
        "matrix_id": 1,
        "rid": 43023,
        "NAME_HE": "חיפה - קריית חיים ושמואל",
        "NAME_EN": "Haifa - Kiryat Haim and Shmuel ",
        "NAME_AR": "حيفا - كريات حاييم وشموئيل",
        "NAME_RU": "Хайфа - Кирьят Хаим и Шмуэль"
    },
    {
        "data": "חיפה - קריית חיים ושמואל",
        "date": "07.10.2024",
        "time": "17:08:39",
        "alertDate": "2024-10-07T17:09:00",
        "category": 1,
        "category_desc": "ירי רקטות וטילים",
        "matrix_id": 1,
        "rid": 42643,
        "NAME_HE": "חיפה - קריית חיים ושמואל",
        "NAME_EN": "Haifa - Kiryat Haim and Shmuel ",
        "NAME_AR": "حيفا - كريات حاييم وشموئيل",
        "NAME_RU": "Хайфа - Кирьят Хаим и Шмуэль"
    },
    {
        "data": "חיפה - קריית חיים ושמואל",
        "date": "05.10.2024",
        "time": "13:26:43",
        "alertDate": "2024-10-05T13:27:00",
        "category": 1,
        "category_desc": "ירי רקטות וטילים",
        "matrix_id": 1,
        "rid": 42153,
        "NAME_HE": "חיפה - קריית חיים ושמואל",
        "NAME_EN": "Haifa - Kiryat Haim and Shmuel ",
        "NAME_AR": "حيفا - كريات حاييم وشموئيل",
        "NAME_RU": "Хайфа - Кирьят Хаим и Шмуэль"
    },
    {
        "data": "חיפה - קריית חיים ושמואל",
        "date": "04.10.2024",
        "time": "07:01:18",
        "alertDate": "2024-10-04T07:01:00",
        "category": 1,
        "category_desc": "ירי רקטות וטילים",
        "matrix_id": 1,
        "rid": 41866,
        "NAME_HE": "חיפה - קריית חיים ושמואל",
        "NAME_EN": "Haifa - Kiryat Haim and Shmuel ",
        "NAME_AR": "حيفا - كريات حاييم وشموئيل",
        "NAME_RU": "Хайфа - Кирьят Хаим и Шмуэль"
    },
    {
        "data": "חיפה - קריית חיים ושמואל",
        "date": "03.10.2024",
        "time": "21:48:21",
        "alertDate": "2024-10-03T21:48:00",
        "category": 1,
        "category_desc": "ירי רקטות וטילים",
        "matrix_id": 1,
        "rid": 41830,
        "NAME_HE": "חיפה - קריית חיים ושמואל",
        "NAME_EN": "Haifa - Kiryat Haim and Shmuel ",
        "NAME_AR": "حيفا - كريات حاييم وشموئيل",
        "NAME_RU": "Хайфа - Кирьят Хаим и Шмуэль"
    },
    {
        "data": "חיפה - קריית חיים ושמואל",
        "date": "01.10.2024",
        "time": "16:10:52",
        "alertDate": "2024-10-01T16:11:00",
        "category": 1,
        "category_desc": "ירי רקטות וטילים",
        "matrix_id": 1,
        "rid": 39493,
        "NAME_HE": "חיפה - קריית חיים ושמואל",
        "NAME_EN": "Haifa - Kiryat Haim and Shmuel ",
        "NAME_AR": "حيفا - كريات حاييم وشموئيل",
        "NAME_RU": "Хайфа - Кирьят Хаим и Шмуэль"
    },
    {
        "data": "חיפה - קריית חיים ושמואל",
        "date": "29.09.2024",
        "time": "21:15:11",
        "alertDate": "2024-09-29T21:15:00",
        "category": 1,
        "category_desc": "ירי רקטות וטילים",
        "matrix_id": 1,
        "rid": 39289,
        "NAME_HE": "חיפה - קריית חיים ושמואל",
        "NAME_EN": "Haifa - Kiryat Haim and Shmuel ",
        "NAME_AR": "حيفا - كريات حاييم وشموئيل",
        "NAME_RU": "Хайфа - Кирьят Хаим и Шмуэль"
    },
    {
        "data": "חיפה - קריית חיים ושמואל",
        "date": "27.09.2024",
        "time": "08:33:41",
        "alertDate": "2024-09-27T08:34:00",
        "category": 1,
        "category_desc": "ירי רקטות וטילים",
        "matrix_id": 1,
        "rid": 38107,
        "NAME_HE": "חיפה - קריית חיים ושמואל",
        "NAME_EN": "Haifa - Kiryat Haim and Shmuel ",
        "NAME_AR": "حيفا - كريات حاييم وشموئيل",
        "NAME_RU": "Хайфа - Кирьят Хаим и Шмуэль"
    },
    {
        "data": "חיפה - קריית חיים ושמואל",
        "date": "24.09.2024",
        "time": "15:03:50",
        "alertDate": "2024-09-24T15:04:00",
        "category": 1,
        "category_desc": "ירי רקטות וטילים",
        "matrix_id": 1,
        "rid": 37569,
        "NAME_HE": "חיפה - קריית חיים ושמואל",
        "NAME_EN": "Haifa - Kiryat Haim and Shmuel ",
        "NAME_AR": "حيفا - كريات حاييم وشموئيل",
        "NAME_RU": "Хайфа - Кирьят Хаим и Шмуэль"
    },
    {
        "data": "חיפה - קריית חיים ושמואל",
        "date": "23.09.2024",
        "time": "19:43:22",
        "alertDate": "2024-09-23T19:43:00",
        "category": 1,
        "category_desc": "ירי רקטות וטילים",
        "matrix_id": 1,
        "rid": 37325,
        "NAME_HE": "חיפה - קריית חיים ושמואל",
        "NAME_EN": "Haifa - Kiryat Haim and Shmuel ",
        "NAME_AR": "حيفا - كريات حاييم وشموئيل",
        "NAME_RU": "Хайфа - Кирьят Хаим и Шмуэль"
    },
    {
        "data": "חיפה - קריית חיים ושמואל",
        "date": "23.09.2024",
        "time": "17:02:02",
        "alertDate": "2024-09-23T17:02:00",
        "category": 1,
        "category_desc": "ירי רקטות וטילים",
        "matrix_id": 1,
        "rid": 37087,
        "NAME_HE": "חיפה - קריית חיים ושמואל",
        "NAME_EN": "Haifa - Kiryat Haim and Shmuel ",
        "NAME_AR": "حيفا - كريات حاييم وشموئيل",
        "NAME_RU": "Хайфа - Кирьят Хаим и Шмуэль"
    },
    {
        "data": "חיפה - קריית חיים ושמואל",
        "date": "22.09.2024",
        "time": "07:00:02",
        "alertDate": "2024-09-22T07:00:00",
        "category": 1,
        "category_desc": "ירי רקטות וטילים",
        "matrix_id": 1,
        "rid": 36857,
        "NAME_HE": "חיפה - קריית חיים ושמואל",
        "NAME_EN": "Haifa - Kiryat Haim and Shmuel ",
        "NAME_AR": "حيفا - كريات حاييم وشموئيل",
        "NAME_RU": "Хайфа - Кирьят Хаим и Шмуэль"
    }
]