[
    {
        "data": "יסעור",
        "date": "24.11.2024",
        "time": "18:12:22",
        "alertDate": "2024-11-24T18:12:00",
        "category": 1,
        "category_desc": "ירי רקטות וטילים",
        "matrix_id": 1,
        "rid": 52387,
        "NAME_HE": "יסעור",
        "NAME_EN": "Yasur",
        "NAME_AR": "يسعور",
        "NAME_RU": "Ясур"
    },
    {
        "data": "יסעור",
        "date": "15.11.2024",
        "time": "09:01:07",
        "alertDate": "2024-11-15T09:01:00",
        "category": 1,
        "category_desc": "ירי רקטות וטילים",
        "matrix_id": 1,
        "rid": 50895,
        "NAME_HE": "יסעור",
        "NAME_EN": "Yasur",
        "NAME_AR": "يسعور",
        "NAME_RU": "Ясур"
    },
    {
        "data": "יסעור",
        "date": "11.11.2024",
        "time": "16:02:20",
        "alertDate": "2024-11-11T16:02:00",
        "category": 1,
        "category_desc": "ירי רקטות וטילים",
        "matrix_id": 1,
        "rid": 50184,
        "NAME_HE": "יסעור",
        "NAME_EN": "Yasur",
        "NAME_AR": "يسعور",
        "NAME_RU": "Ясур"
    },
    {
        "data": "יסעור",
        "date": "08.11.2024",
        "time": "15:54:20",
        "alertDate": "2024-11-08T15:54:00",
        "category": 1,
        "category_desc": "ירי רקטות וטילים",
        "matrix_id": 1,
        "rid": 49770,
        "NAME_HE": "יסעור",
        "NAME_EN": "Yasur",
        "NAME_AR": "يسعور",
        "NAME_RU": "Ясур"
    },
    {
        "data": "יסעור",
        "date": "02.11.2024",
        "time": "11:05:38",
        "alertDate": "2024-11-02T11:06:00",
        "category": 1,
        "category_desc": "ירי רקטות וטילים",
        "matrix_id": 1,
        "rid": 48623,
        "NAME_HE": "יסעור",
        "NAME_EN": "Yasur",
        "NAME_AR": "يسعور",
        "NAME_RU": "Ясур"
    },
    {
        "data": "יסעור",
        "date": "30.10.2024",
        "time": "17:29:47",
        "alertDate": "2024-10-30T17:30:00",
        "category": 2,
        "category_desc": "חדירת כלי טיס עוין",
        "matrix_id": 6,
        "rid": 48161,
        "NAME_HE": "יסעור",
        "NAME_EN": "Yasur",
        "NAME_AR": "يسعور",
        "NAME_RU": "Ясур"
    },
    {
        "data": "יסעור",
        "date": "21.10.2024",
        "time": "12:28:43",
        "alertDate": "2024-10-21T12:29:00",
        "category": 1,
        "category_desc": "ירי רקטות וטילים",
        "matrix_id": 1,
        "rid": 45994,
        "NAME_HE": "יסעור",
        "NAME_EN": "Yasur",
        "NAME_AR": "يسعور",
        "NAME_RU": "Ясур"
    },
    {
        "data": "יסעור",
        "date": "19.10.2024",
        "time": "12:25:26",
        "alertDate": "2024-10-19T12:25:00",
        "category": 1,
        "category_desc": "ירי רקטות וטילים",
        "matrix_id": 1,
        "rid": 45462,
        "NAME_HE": "יסעור",
        "NAME_EN": "Yasur",
        "NAME_AR": "يسعور",
        "NAME_RU": "Ясур"
    },
    {
        "data": "יסעור",
        "date": "18.10.2024",
        "time": "06:59:29",
        "alertDate": "2024-10-18T06:59:00",
        "category": 1,
        "category_desc": "ירי רקטות וטילים",
        "matrix_id": 1,
        "rid": 45236,
        "NAME_HE": "יסעור",
        "NAME_EN": "Yasur",
        "NAME_AR": "يسعور",
        "NAME_RU": "Ясур"
    },
    {
        "data": "יסעור",
        "date": "17.10.2024",
        "time": "07:29:02",
        "alertDate": "2024-10-17T07:29:00",
        "category": 1,
        "category_desc": "ירי רקטות וטילים",
        "matrix_id": 1,
        "rid": 45096,
        "NAME_HE": "יסעור",
        "NAME_EN": "Yasur",
        "NAME_AR": "يسعور",
        "NAME_RU": "Ясур"
    },
    {
        "data": "יסעור",
        "date": "13.10.2024",
        "time": "09:44:41",
        "alertDate": "2024-10-13T09:45:00",
        "category": 1,
        "category_desc": "ירי רקטות וטילים",
        "matrix_id": 1,
        "rid": 43982,
        "NAME_HE": "יסעור",
        "NAME_EN": "Yasur",
        "NAME_AR": "يسعور",
        "NAME_RU": "Ясур"
    },
    {
        "data": "יסעור",
        "date": "13.10.2024",
        "time": "09:01:24",
        "alertDate": "2024-10-13T09:01:00",
        "category": 1,
        "category_desc": "ירי רקטות וטילים",
        "matrix_id": 1,
        "rid": 43977,
        "NAME_HE": "יסעור",
        "NAME_EN": "Yasur",
        "NAME_AR": "يسعور",
        "NAME_RU": "Ясур"
    },
    {
        "data": "יסעור",
        "date": "12.10.2024",
        "time": "15:13:52",
        "alertDate": "2024-10-12T15:14:00",
        "category": 1,
        "category_desc": "ירי רקטות וטילים",
        "matrix_id": 1,
        "rid": 43808,
        "NAME_HE": "יסעור",
        "NAME_EN": "Yasur",
        "NAME_AR": "يسعور",
        "NAME_RU": "Ясур"
    },
    {
        "data": "יסעור",
        "date": "11.10.2024",
        "time": "17:21:46",
        "alertDate": "2024-10-11T17:22:00",
        "category": 1,
        "category_desc": "ירי רקטות וטילים",
        "matrix_id": 1,
        "rid": 43623,
        "NAME_HE": "יסעור",
        "NAME_EN": "Yasur",
        "NAME_AR": "يسعور",
        "NAME_RU": "Ясур"
    },
    {
        "data": "יסעור",
        "date": "08.10.2024",
        "time": "12:12:42",
        "alertDate": "2024-10-08T12:13:00",
        "category": 1,
        "category_desc": "ירי רקטות וטילים",
        "matrix_id": 1,
        "rid": 43042,
        "NAME_HE": "יסעור",
        "NAME_EN": "Yasur",
        "NAME_AR": "يسعور",
        "NAME_RU": "Ясур"
    },
    {
        "data": "יסעור",
        "date": "05.10.2024",
        "time": "16:44:45",
        "alertDate": "2024-10-05T16:45:00",
        "category": 1,
        "category_desc": "ירי רקטות וטילים",
        "matrix_id": 1,
        "rid": 42226,
        "NAME_HE": "יסעור",
        "NAME_EN": "Yasur",
        "NAME_AR": "يسعور",
        "NAME_RU": "Ясур"
    },
    {
        "data": "יסעור",
        "date": "04.10.2024",
        "time": "13:00:45",
        "alertDate": "2024-10-04T13:01:00",
        "category": 1,
        "category_desc": "ירי רקטות וטילים",
        "matrix_id": 1,
        "rid": 42016,
        "NAME_HE": "יסעור",
        "NAME_EN": "Yasur",
        "NAME_AR": "يسعور",
        "NAME_RU": "Ясур"
    },
    {
        "data": "יסעור",
        "date": "03.10.2024",
        "time": "21:48:20",
        "alertDate": "2024-10-03T21:48:00",
        "category": 1,
        "category_desc": "ירי רקטות וטילים",
        "matrix_id": 1,
        "rid": 41844,
        "NAME_HE": "יסעור",
        "NAME_EN": "Yasur",
        "NAME_AR": "يسعور",
        "NAME_RU": "Ясур"
    },
    {
        "data": "יסעור",
        "date": "01.10.2024",
        "time": "16:11:01",
        "alertDate": "2024-10-01T16:11:00",
        "category": 1,
        "category_desc": "ירי רקטות וטילים",
        "matrix_id": 1,
        "rid": 39506,
        "NAME_HE": "יסעור",
        "NAME_EN": "Yasur",
        "NAME_AR": "يسعور",
        "NAME_RU": "Ясур"
    },
    {
        "data": "יסעור",
        "date": "29.09.2024",
        "time": "21:15:11",
        "alertDate": "2024-09-29T21:15:00",
        "category": 1,
        "category_desc": "ירי רקטות וטילים",
        "matrix_id": 1,
        "rid": 39302,
        "NAME_HE": "יסעור",
        "NAME_EN": "Yasur",
        "NAME_AR": "يسعور",
        "NAME_RU": "Ясур"
    },
    {
        "data": "יסעור",
        "date": "28.09.2024",
        "time": "10:42:27",
        "alertDate": "2024-09-28T10:42:00",
        "category": 1,
        "category_desc": "ירי רקטות וטילים",
        "matrix_id": 1,
        "rid": 38720,
        "NAME_HE": "יסעור",
        "NAME_EN": "Yasur",
        "NAME_AR": "يسعور",
        "NAME_RU": "Ясур"
    },
    {
        "data": "יסעור",
        "date": "28.09.2024",
        "time": "09:36:10",
        "alertDate": "2024-09-28T09:36:00",
        "category": 1,
        "category_desc": "ירי רקטות וטילים",
        "matrix_id": 1,
        "rid": 38597,
        "NAME_HE": "יסעור",
        "NAME_EN": "Yasur",
        "NAME_AR": "يسعور",
        "NAME_RU": "Ясур"
    },
    {
        "data": "יסעור",
        "date": "28.09.2024",
        "time": "07:59:03",
        "alertDate": "2024-09-28T07:59:00",
        "category": 1,
        "category_desc": "ירי רקטות וטילים",
        "matrix_id": 1,
        "rid": 38230,
        "NAME_HE": "יסעור",
        "NAME_EN": "Yasur",
        "NAME_AR": "يسعور",
        "NAME_RU": "Ясур"
    },
    {
        "data": "יסעור",
        "date": "24.09.2024",
        "time": "15:03:24",
        "alertDate": "2024-09-24T15:03:00",
        "category": 1,
        "category_desc": "ירי רקטות וטילים",
        "matrix_id": 1,
        "rid": 37563,
        "NAME_HE": "יסעור",
        "NAME_EN": "Yasur",
        "NAME_AR": "يسعور",
        "NAME_RU": "Ясур"
    },
    {
        "data": "יסעור",
        "date": "24.09.2024",
        "time": "13:57:44",
        "alertDate": "2024-09-24T13:58:00",
        "category": 1,
        "category_desc": "ירי רקטות וטילים",
        "matrix_id": 1,
        "rid": 37535,
        "NAME_HE": "יסעור",
        "NAME_EN": "Yasur",
        "NAME_AR": "يسعور",
        "NAME_RU": "Ясур"
    },
    {
        "data": "יסעור",
        "date": "24.09.2024",
        "time": "07:42:34",
        "alertDate": "2024-09-24T07:43:00",
        "category": 1,
        "category_desc": "ירי רקטות וטילים",
        "matrix_id": 1,
        "rid": 37420,
        "NAME_HE": "יסעור",
        "NAME_EN": "Yasur",
        "NAME_AR": "يسعور",
        "NAME_RU": "Ясур"
    },
    {
        "data": "יסעור",
        "date": "22.09.2024",
        "time": "06:31:28",
        "alertDate": "2024-09-22T06:31:00",
        "category": 1,
        "category_desc": "ירי רקטות וטילים",
        "matrix_id": 1,
        "rid": 36790,
        "NAME_HE": "יסעור",
        "NAME_EN": "Yasur",
        "NAME_AR": "يسعور",
        "NAME_RU": "Ясур"
    }
]